README.md
setup.py
nmlu/__init__.py
nmlu/eda.py
nmlu/etl.py
nmlu/model_analysis.py
nmlu/model_utils.py
nmlu/test_etl.py
nmlu/utils.py
nmlu.egg-info/PKG-INFO
nmlu.egg-info/SOURCES.txt
nmlu.egg-info/dependency_links.txt
nmlu.egg-info/not-zip-safe
nmlu.egg-info/top_level.txt
nmlu/qinspect/__init__.py
nmlu/qinspect/common.py
nmlu/qinspect/console.py
nmlu/qinspect/nb.py