Metadata-Version: 1.0
Name: nmlu
Version: 0.10
Summary: Nano Machine Learning utilities toolkit
Home-page: https://github.com/NeuronQ/nmlu
Author: Andrei Anton
Author-email: io@neuronq.ro
License: MIT
Platform: UNKNOWN
